anchor/__init__.py
anchor/__main__.py
anchor/cli.py
anchor/core/__init__.py
anchor/core/contexts.py
anchor/core/engine.py
anchor/core/history.py
anchor/core/mainfest.py
anchor/core/markdown_parser.py
anchor/core/memory.py
anchor/core/models.py
anchor/core/parser.py
anchor/core/policy_loader.py
anchor/core/verdicts.py
anchor_audit-2.1.1.dist-info/licenses/LICENSE
anchor_audit-2.1.1.dist-info/METADATA
anchor_audit-2.1.1.dist-info/WHEEL
anchor_audit-2.1.1.dist-info/entry_points.txt
anchor_audit-2.1.1.dist-info/top_level.txt
anchor_audit-2.1.1.dist-info/RECORD
