Metadata-Version: 2.4
Name: anchor-audit
Version: 2.1.1
Summary: The Federated Governance Engine for AI (FINOS/OSFF Compliant)
Home-page: https://github.com/Tanishq1030/anchor
Author: Tanishq
Author-email: your.email@example.com
Classifier: Development Status :: 4 - Beta
Classifier: Intended Audience :: Developers
Classifier: Topic :: Software Development :: Quality Assurance
Classifier: License :: OSI Approved :: MIT License
Classifier: Programming Language :: Python :: 3
Requires-Python: >=3.8
License-File: LICENSE
Requires-Dist: click
Requires-Dist: pyyaml
Requires-Dist: tree-sitter>=0.22.0
Requires-Dist: tree-sitter-python
Requires-Dist: requests
Dynamic: author
Dynamic: author-email
Dynamic: classifier
Dynamic: description
Dynamic: description-content-type
Dynamic: home-page
Dynamic: license-file
Dynamic: requires-dist
Dynamic: requires-python
Dynamic: summary
